whispool-0.1.2.dist-info/METADATA
whispool-0.1.2.dist-info/WHEEL
whispool/py_whispool.py
whispool/__init__.py
whispool/whispool.cpython-39-darwin.so
whispool-0.1.2.dist-info/RECORD
