Metadata-Version: 2.1
Name: whispool
Version: 0.1.2
Classifier: Programming Language :: Python
